m3u8_downloader/__init__.py
m3u8_downloader/ffmpeg_util.py
m3u8_downloader/m3u8_downloader.py
m3u8_downloader/test.py
m3u8_downloader-1.0.3.dist-info/DESCRIPTION.rst
m3u8_downloader-1.0.3.dist-info/METADATA
m3u8_downloader-1.0.3.dist-info/RECORD
m3u8_downloader-1.0.3.dist-info/WHEEL
m3u8_downloader-1.0.3.dist-info/dependency_links.txt
m3u8_downloader-1.0.3.dist-info/metadata.json
m3u8_downloader-1.0.3.dist-info/top_level.txt
