Metadata-Version: 2.0
Name: m3u8-downloader
Version: 1.0.3
Summary: 这是一个m3u8视频地址下载器。 This is a downloading tool for m3u8 urls.
Home-page: http://www.fr4nk.cn
Author: Frank Yang
Author-email: lxyangfan@gmail.com
License: MIT License
Platform: UNKNOWN
Requires-Dist: beautifulsoup4 (==4.6.0)
Requires-Dist: lxml (==4.1.0)
Requires-Dist: requests (==2.18.4)
